{
  "mani1": {
    "colorName": "Acorn",
    "colorId": "D527",
    "maniImg": "https://i.imgur.com/v4zQmFO.jpg",
    "maniInspo": "My Work",
    "difficultyLevel": 1,
    "uid": "B8nJMa97wCcVm5QJbiYDwsJ4lH23"
  },
  "mani2": {
    "colorName": "Madam",
    "colorId": "D495",
    "maniImg": "https://i.imgur.com/orDMwn6.jpg",
    "maniInspo": "My Work",
    "difficultyLevel": 3,
    "uid": "B8nJMa97wCcVm5QJbiYDwsJ4lH23"
  },
  "mani3": {
    "colorName": "Cornstalk",
    "colorId": "D528",
	  "maniImg": "https://i.imgur.com/fqq3O6P.jpg",
    "maniInspo": "My Work",
    "difficultyLevel": 1,
    "uid": "B8nJMa97wCcVm5QJbiYDwsJ4lH23"
  },
  "mani4": {
    "colorName": "Agave",
    "colorId": "D320",
	  "maniImg": "https://i.imgur.com/QtPBfUQ.jpg",
    "maniInspo": "My Work",
    "difficultyLevel": 1,
    "uid": "B8nJMa97wCcVm5QJbiYDwsJ4lH23"
  },
  "mani5": {
    "colorName": "Rhea",
    "colorId": "D168",
	  "maniImg": "https://i.imgur.com/51qCUi3.jpg",
    "maniInspo": "My Work",
    "difficultyLevel": 1,
    "uid": "B8nJMa97wCcVm5QJbiYDwsJ4lH23"
  },
  "mani6": {
    "colorName": "Reef",
    "colorId": "D543",
	  "maniImg": "https://i.imgur.com/R1d2L3o.jpg",
    "maniInspo": "My Work",
    "difficultyLevel": 1,
    "uid": "B8nJMa97wCcVm5QJbiYDwsJ4lH23"
  },
  "mani7": {
    "colorName": "Torch",
    "colorId": "GC5",
	  "maniImg": "https://i.imgur.com/TWG8R5F.jpg",
    "maniInspo": "My Work",
    "difficultyLevel": 1,
    "uid": "B8nJMa97wCcVm5QJbiYDwsJ4lH23"
  },
  "mani8": {
    "colorName": "Aurora",
    "colorId": "D171",
	  "maniImg": "https://i.imgur.com/TagNbVb.jpg",
    "maniInspo": "My Work",
    "difficultyLevel": 2,
    "uid": "B8nJMa97wCcVm5QJbiYDwsJ4lH23"
  },
  "mani9": {
    "colorName": "Lola",
    "colorId": "D363",
	  "maniImg": "https://i.imgur.com/EFOcHDH.jpg",
    "maniInspo": "My Work",
    "difficultyLevel": 2,
    "uid": "B8nJMa97wCcVm5QJbiYDwsJ4lH23"
  },
  "mani10": {
    "colorName": "Agave",
    "colorId": "D320",
	  "maniImg": "https://i.imgur.com/92lkVle.jpg",
    "maniInspo": "Inspiration",
    "difficultyLevel": 1,
    "uid": "B8nJMa97wCcVm5QJbiYDwsJ4lH23"
  },
  "mani11": {
    "colorName": "Pomegranate",
    "colorId": "D529",
	  "maniImg": "https://i.imgur.com/KYyklJE.jpg",
    "maniInspo": "My Work",
    "difficultyLevel": 3,
    "uid": "B8nJMa97wCcVm5QJbiYDwsJ4lH23"
  },
  "mani12": {
    "colorName": "Agave",
    "colorId": "D320",
	  "maniImg": "https://i.imgur.com/HZyhRib.jpg",
    "maniInspo": "My Work",
    "difficultyLevel": 1,
    "uid": "B8nJMa97wCcVm5QJbiYDwsJ4lH23"
  },
  "mani13": {
    "colorName": "Spiced",
    "colorId": "D532",
	  "maniImg": "https://i.imgur.com/opQ7NaM.jpg",
    "maniInspo": "My Work",
    "difficultyLevel": 2,
    "uid": "B8nJMa97wCcVm5QJbiYDwsJ4lH23"
  },
  "mani14": {
    "colorName": "Amber",
    "colorId": "D530",
	  "maniImg": "https://i.imgur.com/opQ7NaM.jpg",
    "maniInspo": "My Work",
    "difficultyLevel": 2,
    "uid": "B8nJMa97wCcVm5QJbiYDwsJ4lH23"
  },
  "mani15": {
    "colorName": "Tender",
    "colorId": "D131",
	  "maniImg": "https://i.imgur.com/15svaAz.jpg",
    "maniInspo": "My Work",
    "difficultyLevel": 1,
    "uid": "B8nJMa97wCcVm5QJbiYDwsJ4lH23"
  },
  "mani16": {
    "colorName": "Agave",
    "colorId": "D320",
	  "maniImg": "https://i.imgur.com/RZOL1O3.jpg",
    "maniInspo": "Inspiration",
    "difficultyLevel": 1,
    "uid": "B8nJMa97wCcVm5QJbiYDwsJ4lH23"
  },
  "mani17": {
    "colorName": "Agave",
    "colorId": "D320",
	  "maniImg": "https://i.imgur.com/wVDn3aa.jpg",
    "maniInspo": "Inspiration",
    "difficultyLevel": 3,
    "uid": "B8nJMa97wCcVm5QJbiYDwsJ4lH23"
  },
  "mani18": {
    "colorName": "Agave",
    "colorId": "D320",
	  "maniImg": "https://i.imgur.com/nlBYkKt.jpg",
    "maniInspo": "Inspiration",
    "difficultyLevel": 1,
    "uid": "B8nJMa97wCcVm5QJbiYDwsJ4lH23"
  },
  "mani19": {
    "colorName": "Agave",
    "colorId": "D320",
	  "maniImg": "https://i.imgur.com/MsuUgkP.jpg",
    "maniInspo": "Inspiration",
    "difficultyLevel": 3,
    "uid": "B8nJMa97wCcVm5QJbiYDwsJ4lH23"
  },
  "mani20": {
    "colorName": "Agave",
    "colorId": "D320",
	  "maniImg": "https://i.imgur.com/AH0QrxR.jpg",
    "maniInspo": "Inspiration",
    "difficultyLevel": 1,
    "uid": "B8nJMa97wCcVm5QJbiYDwsJ4lH23"
  },
  "mani21": {
    "colorName": "Agave",
    "colorId": "D320",
	  "maniImg": "https://i.imgur.com/7TLiRGf.jpg",
    "maniInspo": "Inspiration",
    "difficultyLevel": 1,
    "uid": "B8nJMa97wCcVm5QJbiYDwsJ4lH23"
  },
  "mani22": {
    "colorName": "Agave",
    "colorId": "D320",
	  "maniImg": "https://i.imgur.com/5sxjgxF.jpg",
    "maniInspo": "Inspiration",
    "difficultyLevel": 3,
    "uid": "B8nJMa97wCcVm5QJbiYDwsJ4lH23"
  },
  "mani23": {
    "colorName": "Agave",
    "colorId": "D320",
	  "maniImg": "https://i.imgur.com/X44396X.jpg",
    "maniInspo": "Inspiration",
    "difficultyLevel": 1,
    "uid": "B8nJMa97wCcVm5QJbiYDwsJ4lH23"
  },
  "mani24": {
    "colorName": "Agave",
    "colorId": "D320",
	  "maniImg": "https://i.imgur.com/G7LFTjG.jpg",
    "maniInspo": "Inspiration",
    "difficultyLevel": 1,
    "uid": "B8nJMa97wCcVm5QJbiYDwsJ4lH23"
  }
}
